dls_pmac_control/CSstatus.py
dls_pmac_control/GlobalStatus.py
dls_pmac_control/__init__.py
dls_pmac_control/__main__.py
dls_pmac_control/_version.py
dls_pmac_control/axissettings.py
dls_pmac_control/commsThread.py
dls_pmac_control/energise.py
dls_pmac_control/formAxisSettings.ui
dls_pmac_control/formCSStatus.ui
dls_pmac_control/formControl.ui
dls_pmac_control/formEnergise.ui
dls_pmac_control/formGather.ui
dls_pmac_control/formGlobalStatus.ui
dls_pmac_control/formLogin.ui
dls_pmac_control/formPpmacAxisSettings.ui
dls_pmac_control/formPpmacCSStatus.ui
dls_pmac_control/formStatus.ui
dls_pmac_control/formWatches.ui
dls_pmac_control/gather.py
dls_pmac_control/gatherchannel.py
dls_pmac_control/greenLedOff.png
dls_pmac_control/greenLedOn.png
dls_pmac_control/led-amber.png
dls_pmac_control/login.py
dls_pmac_control/ppmacgather.py
dls_pmac_control/re
dls_pmac_control/redLedOff.png
dls_pmac_control/redLedOn.png
dls_pmac_control/signal
dls_pmac_control/status.py
dls_pmac_control/sys
dls_pmac_control/types
dls_pmac_control/ui_formAxisSettings.py
dls_pmac_control/ui_formCSStatus.py
dls_pmac_control/ui_formControl.py
dls_pmac_control/ui_formEnergise.py
dls_pmac_control/ui_formGather.py
dls_pmac_control/ui_formGlobalStatus.py
dls_pmac_control/ui_formLogin.py
dls_pmac_control/ui_formPpmacAxisSettings.py
dls_pmac_control/ui_formPpmacCSStatus.py
dls_pmac_control/ui_formStatus.py
dls_pmac_control/ui_formWatches.py
dls_pmac_control/watches.py
dls_pmaccontrol-3.2.3.dist-info/LICENSE
dls_pmaccontrol-3.2.3.dist-info/METADATA
dls_pmaccontrol-3.2.3.dist-info/WHEEL
dls_pmaccontrol-3.2.3.dist-info/entry_points.txt
dls_pmaccontrol-3.2.3.dist-info/top_level.txt
dls_pmaccontrol-3.2.3.dist-info/RECORD
